MANIFEST.in
README.md
setup.cfg
setup.py
style/__init__.py
style.py.egg-info/PKG-INFO
style.py.egg-info/SOURCES.txt
style.py.egg-info/dependency_links.txt
style.py.egg-info/top_level.txt